textSummarizer/__init__.py
textSummarizer/main.py
terminaltexttools-1.0.0.dist-info/METADATA
terminaltexttools-1.0.0.dist-info/WHEEL
terminaltexttools-1.0.0.dist-info/entry_points.txt
terminaltexttools-1.0.0.dist-info/top_level.txt
terminaltexttools-1.0.0.dist-info/RECORD
