Metadata-Version: 2.2
Name: TerminaltextTools
Version: 1.0.0
Summary: A CLI tool to summarize text files using GPT-3.5-turbo
Author: Abdur Rehman Tariq
Classifier: Programming Language :: Python :: 3
Classifier: Operating System :: OS Independent
Requires-Dist: openai
Requires-Dist: textual
Requires-Dist: python-docx
Requires-Dist: chardet
Dynamic: author
Dynamic: classifier
Dynamic: requires-dist
Dynamic: summary
